{
  "kind": "singleType",
  "collectionName": "profiles",
  "info": {
    "singularName": "profile",
    "pluralName": "profiles",
    "displayName": "Profile"
  },
  "options": {
    "draftAndPublish": true
  },
  "pluginOptions": {},
  "attributes": {
    "Title": {
      "type": "string"
    },
    "Paragraph": {
      "type": "blocks"
    },
    "Snapshot": {
      "allowedTypes": [
        "images",
        "files",
        "videos",
        "audios"
      ],
      "type": "media",
      "multiple": false
    }
  }
}
